{
    "titre":"Codeurs En Seine",
    "programme":{
        "jours":[
            {
                "title": "day1",
                "date": "27/10/2014",
                "tracks":[

                 {
                        "type":"java",
                        "talks":[
                            {"id":51 , 
                            "format":"conference", 
                            "url":"", 
                            "title":"50 nouvelles choses que l'on peut faire avec Java 8",
                             "description":"Java 8, c'est bien sûr l'arrivée des lambdas, des Stream et des Collectors. Mais ce n'est pas que cela. Plein de nouvelles choses sont aussi offertes : un nouvelle API pour les dates, un nouveau moteur Javascript, une nouvelle version de JavaFX, une nouvelle ConcurrentHashMap, une nouvelle HashMap, des nouveautés dans le domaine de la concurrence, et toutes sortes de petites choses qui vont nous faciliter la vie, que l'on se propose de passer en revue ici."
                             }
                         ]
                    },
                    {
                        "type":"java",
                        "talks":[
                            {"id":101 ,  
                            "format":"conference", 
                            "url":"", 
                            "title":"La révolution Docker",
                             "description":"En très peu de temps, Docker a su s'imposer comme un standard de facto dans le monde du Cloud, ne laissant aucun fournisseur impassible. A mi-chemin entre IaaS et PaaS, Docker brouille les cartes et ouvre de nouvelles opportunités. Au cours de ce talk, nous vous présenterons ce qu'est techniquement Docker, son impact sur l'écosystème et comment vous pouvez le mettre à profit pour vos propres développements."
                             }
                         ]
                    }
                ]
            }
        ]
    }
}

